sklearn_mlmlm/classifiers.py
sklearn_mlmlm-1.0.0.dist-info/LICENSE
sklearn_mlmlm-1.0.0.dist-info/METADATA
sklearn_mlmlm-1.0.0.dist-info/WHEEL
sklearn_mlmlm-1.0.0.dist-info/RECORD
